{
	"configurations" : 
	[
		{
			"directories" : 
			[
				{
					"build" : ".",
					"jsonFile" : "directory-.-Debug-d0094a50bb2071803777.json",
					"minimumCMakeVersion" : 
					{
						"string" : "3.20"
					},
					"projectIndex" : 0,
					"source" : ".",
					"targetIndexes" : 
					[
						0,
						1,
						2,
						3,
						4,
						5
					]
				}
			],
			"name" : "Debug",
			"projects" : 
			[
				{
					"directoryIndexes" : 
					[
						0
					],
					"name" : "TD03",
					"targetIndexes" : 
					[
						0,
						1,
						2,
						3,
						4,
						5
					]
				}
			],
			"targets" : 
			[
				{
					"directoryIndex" : 0,
					"id" : "exo1::@6890427a1f51a3e7e1df",
					"jsonFile" : "target-exo1-Debug-3ac552607d31e829e8bc.json",
					"name" : "exo1",
					"projectIndex" : 0
				},
				{
					"directoryIndex" : 0,
					"id" : "exo2::@6890427a1f51a3e7e1df",
					"jsonFile" : "target-exo2-Debug-04b1db3d87e82e709251.json",
					"name" : "exo2",
					"projectIndex" : 0
				},
				{
					"directoryIndex" : 0,
					"id" : "exo3::@6890427a1f51a3e7e1df",
					"jsonFile" : "target-exo3-Debug-254e12ad5e1d359ae668.json",
					"name" : "exo3",
					"projectIndex" : 0
				},
				{
					"directoryIndex" : 0,
					"id" : "exo4::@6890427a1f51a3e7e1df",
					"jsonFile" : "target-exo4-Debug-abbe70f59365fdc7d5e4.json",
					"name" : "exo4",
					"projectIndex" : 0
				},
				{
					"directoryIndex" : 0,
					"id" : "exo5::@6890427a1f51a3e7e1df",
					"jsonFile" : "target-exo5-Debug-62d76932207798be627d.json",
					"name" : "exo5",
					"projectIndex" : 0
				},
				{
					"directoryIndex" : 0,
					"id" : "exo6::@6890427a1f51a3e7e1df",
					"jsonFile" : "target-exo6-Debug-3720969746bbefa9359c.json",
					"name" : "exo6",
					"projectIndex" : 0
				}
			]
		}
	],
	"kind" : "codemodel",
	"paths" : 
	{
		"build" : "C:/IMAC/C++/td3/build",
		"source" : "C:/IMAC/C++/td3"
	},
	"version" : 
	{
		"major" : 2,
		"minor" : 7
	}
}
